setup.cfg
setup.py
tcp_chat/Node.py
tcp_chat/__init__.py
tcp_chat/client.py
tcp_chat/server.py
tcp_chat/tcp_chat.py
tcp_chat.egg-info/PKG-INFO
tcp_chat.egg-info/SOURCES.txt
tcp_chat.egg-info/dependency_links.txt
tcp_chat.egg-info/entry_points.txt
tcp_chat.egg-info/requires.txt
tcp_chat.egg-info/top_level.txt