Metadata-Version: 1.1
Name: tcp-chat
Version: 0.1.1
Summary: A chat app built over TCP
Home-page: https://github.com/pdhoot/tcp_chat
Author: Punit Dhoot
Author-email: punitdhoot1@gmail.com
License: MIT
Download-URL: https://github.com/pdhoot/tcp_chat/tarball/0.1
Keywords: chat,tcp-chat
Platform: UNKNOWN
